SecretColors/__init__.py
SecretColors/utils.py
SecretColors/cmaps/__init__.py
SecretColors/cmaps/brewer.py
SecretColors/cmaps/colorblind.py
SecretColors/cmaps/parent.py
SecretColors/cmaps/tableau.py
SecretColors/data/__init__.py
SecretColors/data/constants.py
SecretColors/data/rgb_xyz.py
SecretColors/data/cmaps/__init__.py
SecretColors/data/cmaps/brewer.py
SecretColors/data/cmaps/colorblind.py
SecretColors/data/cmaps/tableau.py
SecretColors/data/names/__init__.py
SecretColors/data/names/w3.py
SecretColors/data/names/x11.py
SecretColors/data/palettes/__init__.py
SecretColors/data/palettes/brewer.py
SecretColors/data/palettes/clarity.py
SecretColors/data/palettes/ibm.py
SecretColors/data/palettes/material.py
SecretColors/data/palettes/parent.py
SecretColors/data/palettes/tableau.py
SecretColors/data/palettes/todo.py
SecretColors/helpers/__init__.py
SecretColors/helpers/decorators.py
SecretColors/helpers/logging.py
SecretColors/helpers/rxutils.py
SecretColors/models/__init__.py
SecretColors/models/base.py
SecretColors/models/objects.py
SecretColors/models/palette.py
test/__init__.py
test/test_base.py
test/test_objects.py
test/test_palette.py
test/test_utils.py
SecretColors-1.2.6.dist-info/LICENSE
SecretColors-1.2.6.dist-info/METADATA
SecretColors-1.2.6.dist-info/WHEEL
SecretColors-1.2.6.dist-info/top_level.txt
SecretColors-1.2.6.dist-info/RECORD
