Metadata-Version: 2.1
Name: SecretColors
Version: 1.2.6
Summary: A small package for fantastic color palette
Home-page: https://github.com/secretBiology/SecretColors
Author: Rohit Suratekar
Author-email: rohitsuratekar@gmail.com
License: MIT License
Platform: UNKNOWN
Classifier: Programming Language :: Python :: 3.8
Classifier: License :: OSI Approved :: MIT License
Classifier: Operating System :: OS Independent
License-File: LICENSE
